<?xml version="1.0" encoding="UTF-8"?>
<entity-mappings version="2.3" xmlns="http://www.eclipse.org/eclipselink/xsds/persistence/orm" xmlns:xsi="http://www.w3.org/2001/XMLSchema-instance" xsi:schemaLocation="http://www.eclipse.org/eclipselink/xsds/persistence/orm http://www.eclipse.org/eclipselink/xsds/eclipselink_orm_2_3.xsd">
    <entity metadata-complete="true" name="IdGenerator" class="net.jescort.domain.IdGenerator" access="PROPERTY">
        <table name="id_generator"/>
        <attributes>
            <id name="name">
                <column name="`name`" unique="true"/>
            </id>
            <basic name="value">
                <column name="`value`" insertable="true" updatable="true" unique="false"/>
            </basic>
        </attributes>
    </entity>
</entity-mappings>
